[{"r":"241177","n":"RIJVANA BANO","f":"RIHAJ QURESHI","c":"","res":"PASS"},{"r":"322449","n":"MUSHIRA KAUSHAR","f":"ABDUL RASHID QURESHI","c":"","res":"PASS"},{"r":"245331","n":"RUKSHAR BANO","f":"NAJRUDEEN QURESHI","c":"","res":"PASS"},{"r":"184143","n":"HEENA","f":"BARKAT ALI QURESHI","c":"","res":"PASS"},{"r":"195565","n":"NAZERA QURESH","f":"ALAUDDIN QURESH","c":"","res":"PASS"},{"r":"181745","n":"MUHAMMED HUMAID QURAISHI","f":"NIZAMUDDIN QURAISHI","c":"","res":"PASS"},{"r":"298149","n":"AZHARUDDIN QURESHI","f":"HABIB KHAN QURESHI","c":"","res":"PASS"},{"r":"322294","n":"SHADAB ASHRAF","f":"ABDUL KHALIK QURESHI","c":"","res":"PASS"},{"r":"192376","n":"SOFIYA QURESHI","f":"SHAHJAD BABU QURESHI","c":"","res":"PASS"},{"r":"155807","n":"SHAHEEN PARVEEN","f":"ABDUL QUYYOOM MANSURY","c":"","res":"PASS"},{"r":"281287","n":"NASARUDDEEN QURESHI","f":"SHARFUDDEEN QURESHI","c":"","res":"PASS"},{"r":"233351","n":"KAMRAN ALI","f":"QURBAN ALI","c":"","res":"PASS"},{"r":"280354","n":"SALEEM QURESHI","f":"SHAKIR QURESHI","c":"","res":"PASS"},{"r":"242502","n":"JAHID QURESHI","f":"SABBIR QURESHI","c":"","res":"PASS"},{"r":"211539","n":"MOHAMMED SHAFAN HASHMI","f":"SHAFI MOHAMMED QURESHI","c":"","res":"PASS"},{"r":"205887","n":"ASLAM QURAISHI","f":"IKRAM QURAISHI","c":"","res":"PASS"}]