[{"r":"321447","n":"HIMANSHU SUTHAR","f":"TULSI RAM SUTHAR","c":"","res":"PASS"},{"r":"329034","n":"JITENDRA BIJARNIYA","f":"TULCHHI RAM BIJARNIYA","c":"","res":"PASS"},{"r":"266775","n":"DALCHAND KUMAWAT","f":"TULSHI RAM KUMAWAT","c":"","res":"PASS"},{"r":"329515","n":"HARI RAM","f":"TULACHHA RAM KUMAWAT","c":"","res":"PASS"},{"r":"330428","n":"NARENDRA GODARA","f":"TULCHI RAM GODARA","c":"","res":"PASS"},{"r":"255032","n":"POOJA BULDAK","f":"TULSI RAM BULDAK","c":"","res":"PASS"},{"r":"194560","n":"RAHUL TUSAWDA","f":"RUPESH KUMAR TUSAWDA","c":"","res":"PASS"},{"r":"184790","n":"RAJPAL JHORAR","f":"TULCHHARAM JHORAR","c":"","res":"PASS"},{"r":"173096","n":"SATYA PRAKASH","f":"TURSI RAM","c":"","res":"PASS"},{"r":"302926","n":"MAHESH SALODIYA","f":"TULSI RAM REGAR","c":"","res":"PASS"},{"r":"295349","n":"GANITA CHOUDHARY","f":"TULCHHA RAM","c":"","res":"PASS"},{"r":"272444","n":"SONU NAGAR","f":"TULSI RAM NAGAR","c":"","res":"PASS"},{"r":"225624","n":"DINESH KUMAR","f":"TULSI RAM","c":"","res":"PASS"},{"r":"244566","n":"DHARMENDRA KUMAR JAT","f":"TULSHI RAM JAT","c":"","res":"PASS"},{"r":"319127","n":"RONAK DANGI","f":"TULSIRAM DANGI","c":"","res":"PASS"},{"r":"180733","n":"NAND LAL KANJAR","f":"TULSIRAM","c":"","res":"PASS"},{"r":"283971","n":"PRIYANSHU SAIN","f":"TULSI RAM SAIN","c":"","res":"PASS"},{"r":"304689","n":"SARASWATI MEENA","f":"TULSEERAM MEENA","c":"","res":"PASS"},{"r":"290537","n":"SURESH JAIVALYA","f":"TULSI RAM","c":"","res":"PASS"},{"r":"313713","n":"GANESH SAINI","f":"TULSI RAM SAINI","c":"","res":"PASS"},{"r":"301470","n":"MAHESH KHATIK","f":"TULSI RAM","c":"","res":"PASS"},{"r":"214090","n":"CHETAN KUMAR SHARMA","f":"TULSI RAM SHARMA","c":"","res":"PASS"},{"r":"319121","n":"NAYAN DAIYAWAT","f":"TULSIRAM DAIYAWAT","c":"","res":"PASS"},{"r":"294258","n":"MULA RAM","f":"TULCHHA RAM","c":"","res":"PASS"},{"r":"322891","n":"MAHIPAL CHAUDHARY","f":"TULCHARAM","c":"","res":"PASS"},{"r":"183715","n":"PAWAN BURIA","f":"TULCHHA RAM","c":"","res":"PASS"},{"r":"158924","n":"RACHNA BAI","f":"TULSI RAM","c":"","res":"PASS"},{"r":"331124","n":"MONIKA","f":"TULCHHA RAM","c":"","res":"PASS"},{"r":"188979","n":"RUPESH KUMAR MEENA","f":"TULASIRAM","c":"","res":"PASS"},{"r":"286349","n":"RIYA NAGAR","f":"TULSI RAM NAGAR","c":"","res":"PASS"},{"r":"175860","n":"BABLESH SAINI","f":"TULSIRAM","c":"","res":"PASS"},{"r":"304386","n":"MAYANK SHARMA","f":"TULSI RAM SHARMA","c":"","res":"PASS"},{"r":"319628","n":"PANNA LAL REGAR","f":"TULSI RAM REGAR","c":"","res":"PASS"},{"r":"293287","n":"RAMAVATAR VAISHANV","f":"TULSI DAS","c":"","res":"PASS"},{"r":"316010","n":"MONU MEENA","f":"TULSIRAM MEENA","c":"","res":"PASS"},{"r":"260867","n":"RAHUL KUMAWAT","f":"TULSIRAM MARWAL","c":"","res":"PASS"},{"r":"262495","n":"ROHIT CHOUDHARY","f":"TULSIRAM","c":"","res":"PASS"},{"r":"330339","n":"MANI RAM","f":"TULCHI RAM","c":"","res":"PASS"},{"r":"291481","n":"SUSHIL KUMAR DUKIYA","f":"TULCHHA RAM","c":"","res":"PASS"},{"r":"300268","n":"NEERAJ JOSHI","f":"TULASI RAM","c":"","res":"PASS"},{"r":"286225","n":"HARSHIT MALAV","f":"TULSI RAM","c":"","res":"PASS"},{"r":"213734","n":"RUCHIKA","f":"TULSI RAM","c":"","res":"PASS"},{"r":"320679","n":"MANOJ KUMAR MEENA","f":"TULSI RAM MEENA","c":"","res":"PASS"},{"r":"274342","n":"PAWAN KUMAR","f":"TULSIRAM","c":"","res":"PASS"},{"r":"322072","n":"DEEPIKA KUMARI AUDICHYA","f":"TULSI RAM AUDICHYA","c":"","res":"PASS"},{"r":"322107","n":"RAKESH JANWA","f":"TULSI RAM JANWA","c":"","res":"PASS"},{"r":"292132","n":"MAHENDRA JAT","f":"TULACHHA RAM","c":"","res":"PASS"},{"r":"184220","n":"JYOTI JAKHTIYA","f":"TULSEERAM","c":"","res":"PASS"},{"r":"321373","n":"GORI SHANKAR LOHAR","f":"TULSI RAM LOHAR","c":"","res":"PASS"},{"r":"183802","n":"KAUSHALYA SIDH","f":"TULCH NATH","c":"","res":"PASS"},{"r":"197961","n":"GANESH NATH","f":"TULACHH NATH","c":"","res":"PASS"},{"r":"218709","n":"POONAM","f":"TULCHHA RAM","c":"","res":"PASS"},{"r":"244466","n":"PRIYANKA POONIYA","f":"TULSI RAM","c":"","res":"PASS"},{"r":"270982","n":"TOGA RAM","f":"TULCHA RAM","c":"","res":"PASS"},{"r":"307366","n":"ANJU KUMARI GARHWAL","f":"TULSI RAM","c":"","res":"PASS"},{"r":"199932","n":"DILEEP SHARMA","f":"TULSI RAM SHARMA","c":"","res":"PASS"},{"r":"189230","n":"ATUL CHOUDHARY","f":"TULSIRAM CHOUDHARY","c":"","res":"PASS"},{"r":"264202","n":"AJAY KUMAR JAJUNDA","f":"TULSI RAM JAT","c":"","res":"PASS"},{"r":"216096","n":"MAHESH KUMAR","f":"TULSA RAM","c":"","res":"PASS"},{"r":"295236","n":"SANTOSH","f":"TULCHHA RAM","c":"","res":"PASS"},{"r":"160131","n":"PRASHANT KUMAR","f":"TULSHI RAM","c":"","res":"PASS"},{"r":"248614","n":"KOMAL DHAYAL","f":"TULSI RAM","c":"","res":"PASS"},{"r":"256401","n":"ASHISH PRAJAPAT","f":"TULSI RAM PRAJAPAT","c":"","res":"PASS"},{"r":"191847","n":"NARENDRA MEENA","f":"TULSIRAM MEENA","c":"","res":"PASS"},{"r":"330460","n":"MANOJ KUMAR","f":"TULSI RAM","c":"","res":"PASS"},{"r":"179045","n":"KANHAIYA LAL KANJAR","f":"TULSI RAM","c":"","res":"PASS"},{"r":"263136","n":"HARIOM","f":"TUNDARAM","c":"","res":"PASS"},{"r":"300487","n":"CHETTNYA JINGAR","f":"TULSI RAM JINGAR","c":"","res":"PASS"},{"r":"197442","n":"SAPNA KUMARI GUNDLA","f":"TULSIRAM","c":"","res":"PASS"},{"r":"153796","n":"ASHVINI TUNGARIYA","f":"KAMLESH KUMAR TUNGARIA","c":"","res":"PASS"},{"r":"223789","n":"KESHAV PAREEK","f":"TULSI RAM","c":"","res":"PASS"},{"r":"328701","n":"MAMTA KULHARI","f":"TULSI RAM","c":"","res":"PASS"},{"r":"306357","n":"ANISHA KASWA","f":"TULACHHARAM","c":"","res":"PASS"},{"r":"192910","n":"RAVI CHAUDHARY","f":"TULSIRAM CHAUDHARY","c":"","res":"PASS"},{"r":"171850","n":"BHERA RAM","f":"TULCHHA RAM","c":"","res":"PASS"},{"r":"195906","n":"VIKRAM SHARMA","f":"TULASIRAM","c":"","res":"PASS"},{"r":"327967","n":"MONIKA","f":"TULCHHA RAM","c":"","res":"PASS"},{"r":"295739","n":"NARENDRA","f":"TULSI RAM","c":"","res":"PASS"},{"r":"316907","n":"NARESH THAGARIA","f":"TULSI DAS VERMA","c":"","res":"PASS"},{"r":"173444","n":"TUSHAR SHARMA","f":"TULSIRAM SHARMA","c":"","res":"PASS"},{"r":"322140","n":"ASHITA KUMARI PUROHIT","f":"TULSI RAM","c":"","res":"PASS"},{"r":"170518","n":"JITENDRA CHOUDHARY","f":"TULSA RAM CHOUDHARY","c":"","res":"PASS"},{"r":"172284","n":"BHARAT CHOUDHARY","f":"TULCHHARAM","c":"","res":"PASS"},{"r":"289177","n":"SONU NAGAR","f":"TULASIRAM","c":"","res":"PASS"},{"r":"190997","n":"HEMANT GOCHAR","f":"TULASIRAM","c":"","res":"PASS"},{"r":"223062","n":"SUNIL KUMAR","f":"TULCHHA RAM","c":"","res":"PASS"},{"r":"311642","n":"BHARAT LAL MEENA","f":"TULASIRAM MEENA","c":"","res":"PASS"},{"r":"303179","n":"KALU RAM MEENA","f":"TULSHI RAM MEENA","c":"","res":"PASS"},{"r":"172622","n":"RAVI KUMAR","f":"TURSHIRAM","c":"","res":"PASS"},{"r":"158002","n":"ANIL KUMAR VERMA","f":"TULSI RAM","c":"","res":"PASS"},{"r":"258647","n":"JITENDRA JAT","f":"TULSI RAM JAT","c":"","res":"PASS"},{"r":"278772","n":"RAMA RAM","f":"TULSA RAM","c":"","res":"PASS"},{"r":"190789","n":"PRAKASH KUMAWAT","f":"TULSIRAM","c":"","res":"PASS"},{"r":"183297","n":"SHIV LAL","f":"TULCHHA RAM","c":"","res":"PASS"},{"r":"248266","n":"SHYAM SUNDAR MEENA","f":"TULSIRAM MEENA","c":"","res":"PASS"},{"r":"319213","n":"KHEMRAJ DANGI","f":"TULASIRAM DANGI","c":"","res":"PASS"},{"r":"301193","n":"DIVYA SALVI","f":"TULSI RAM","c":"","res":"PASS"},{"r":"277585","n":"ABHAY SINGH","f":"TULSA RAM","c":"","res":"PASS"},{"r":"224846","n":"MONIKA","f":"TULSHA RAM","c":"","res":"PASS"},{"r":"327235","n":"SAPNA SAINI","f":"TULARAM SAINI","c":"","res":"PASS"},{"r":"207520","n":"HARDIK DARJI","f":"TULSIRAM DARJI","c":"","res":"PASS"},{"r":"200428","n":"EKATA MEENA","f":"TULSI RAM MEENA","c":"","res":"PASS"},{"r":"296318","n":"RAM PRASAD","f":"TULCHHA RAM","c":"","res":"PASS"},{"r":"241503","n":"PRAVEEN POONIA","f":"TULSI RAM POONIA","c":"","res":"PASS"},{"r":"294669","n":"DEVENDER","f":"TULCHHA RAM","c":"","res":"PASS"},{"r":"194063","n":"PRAVEEN KUMAR MEENA","f":"TULSI RAM MEENA","c":"","res":"PASS"},{"r":"290808","n":"SUNIL","f":"TULCHHA RAM","c":"","res":"PASS"},{"r":"189843","n":"PAWAN KUMAR SAINI","f":"TULSIRAM SAINI","c":"","res":"PASS"},{"r":"289872","n":"MANISH MEHTA","f":"TULSIRAM","c":"","res":"PASS"},{"r":"281456","n":"SANJU","f":"TULCHHA RAM","c":"","res":"PASS"},{"r":"184706","n":"SANWAR MAL","f":"TULCHHARAM JHORAR","c":"","res":"PASS"},{"r":"318762","n":"RAJESH MEGHWAL","f":"TULASI RAM MEGHWAL","c":"","res":"PASS"},{"r":"274800","n":"SURAJ YADVENDU","f":"TULSI RAM YADVENDU","c":"","res":"PASS"},{"r":"167598","n":"SHANI DEVAL","f":"TULSIRAM MEENA","c":"","res":"PASS"},{"r":"174390","n":"DEVAKI GURJAR","f":"TULSIRAM","c":"","res":"PASS"},{"r":"288593","n":"KRISHNA MEENA","f":"TULSIRAM MEENA","c":"","res":"PASS"},{"r":"317365","n":"VINOD JAT","f":"TULSI RAM JAT","c":"","res":"PASS"},{"r":"189004","n":"ABHISHEK BAIRAGI","f":"TULSIRAM BAIRAGI","c":"","res":"PASS"},{"r":"204613","n":"ARCHNA","f":"TULSIRAM SHARMA","c":"","res":"PASS"},{"r":"241354","n":"HUMESH YADAV","f":"TULSIRAM YADAV","c":"","res":"PASS"},{"r":"274213","n":"BRIJESH LODHA","f":"TULSI RAM LODHA","c":"","res":"PASS"},{"r":"218372","n":"KALAWATI","f":"TULSA RAM","c":"","res":"PASS"},{"r":"232534","n":"ARUHI GANGWAR","f":"TULARAM GANGWAR","c":"","res":"PASS"},{"r":"153063","n":"BIMLA JAT","f":"TULSI RAM","c":"","res":"PASS"},{"r":"188626","n":"NAKITA SAINI","f":"TULSHIRAM SAINI","c":"","res":"PASS"},{"r":"293159","n":"RAKESH KUMHAR","f":"TULSI RAM KUMHAR","c":"","res":"PASS"},{"r":"187454","n":"AKASH MEHARA","f":"TULSI RAM MEHARA","c":"","res":"PASS"},{"r":"305502","n":"PANCHI DEVI","f":"TULCHHA RAM","c":"","res":"PASS"},{"r":"320954","n":"AKSHAY LOHAR","f":"TULSI RAM LOHAR","c":"","res":"PASS"},{"r":"170754","n":"BHAGA RAM","f":"TULCHHA RAM","c":"","res":"PASS"},{"r":"320904","n":"DINESH VAIRAGI","f":"TULASI DAS VAIRAGI","c":"","res":"PASS"},{"r":"225986","n":"SONIA","f":"TULCHHA RAM","c":"","res":"PASS"},{"r":"188908","n":"DHARMANDER GURJAR","f":"TULSIRAM GURJAR","c":"","res":"PASS"},{"r":"250907","n":"ANMOL MEENA","f":"TULSI RAM MEENA","c":"","res":"PASS"},{"r":"258355","n":"PUSHKAR","f":"TULSIRAM","c":"","res":"PASS"},{"r":"160087","n":"DINESH CHAND","f":"TULASI RAM","c":"","res":"PASS"},{"r":"331244","n":"KAVITA KUMAWAT","f":"TULSIRAM KUMAWAT","c":"","res":"PASS"},{"r":"293739","n":"POOJA SARAN","f":"TULCHHI RAM","c":"","res":"PASS"},{"r":"290493","n":"PRIYANKA BERWAL","f":"TULCHA RAM BERWAL","c":"","res":"PASS"},{"r":"301940","n":"DHANRAJ MEENA","f":"TULSIRAM MEENA","c":"","res":"PASS"},{"r":"176570","n":"PRADEEP SINGH","f":"TULSI RAM GURJAR","c":"","res":"PASS"},{"r":"309951","n":"VINOD KUMAR","f":"TULSI RAM","c":"","res":"PASS"},{"r":"194097","n":"VISHAL DHAKER","f":"TULSI RAM DHAKER","c":"","res":"PASS"},{"r":"287329","n":"AKASH NAGAR","f":"TULSI RAM","c":"","res":"PASS"},{"r":"269705","n":"UTKARSH NIGAM","f":"TUSHAR NIGAM","c":"","res":"PASS"},{"r":"274776","n":"GAUTAM LOVVANSHI","f":"TULSIRAM LOVVANSHI","c":"","res":"PASS"},{"r":"174057","n":"MANISH KUMAR","f":"TULA RAM","c":"","res":"PASS"},{"r":"271480","n":"MAHENDRA KUMAR","f":"TULSA RAM","c":"","res":"PASS"},{"r":"171208","n":"GAYATREE","f":"TULASA RAM KHILERY","c":"","res":"PASS"},{"r":"213068","n":"MANOHAR LAL","f":"TULSA RAM","c":"","res":"PASS"},{"r":"279867","n":"DEVENDRA","f":"TULCHHA RAM","c":"","res":"PASS"},{"r":"314403","n":"DILKHUSH MEENA","f":"TULSIRAM MEENA","c":"","res":"PASS"},{"r":"288598","n":"UMESH NAGAR","f":"TULSIRAM NAGAR","c":"","res":"PASS"},{"r":"294861","n":"PRAVIN JANGID","f":"TULCHI RAM","c":"","res":"PASS"},{"r":"313668","n":"ASHOK TUNGARIYA","f":"HEMANT TUNGARIYA","c":"","res":"PASS"},{"r":"289653","n":"RAVI MEENA","f":"TULSIRAM MEENA","c":"","res":"PASS"},{"r":"174392","n":"SHAILESH KUMAR","f":"TULSI RAM","c":"","res":"PASS"},{"r":"259544","n":"NARENDRA CHIRANIA","f":"TULSIRAM CHOUDHARY","c":"","res":"PASS"},{"r":"160163","n":"LALIT KUMAR BUNKER","f":"TULASI RAM BUNKER","c":"","res":"PASS"},{"r":"209038","n":"ROSHANLAL PARMAR","f":"TULSIRAM PARMAR","c":"","res":"PASS"},{"r":"292291","n":"SURENDRA","f":"TULCHHA RAM","c":"","res":"PASS"},{"r":"323180","n":"MANISH BHATI","f":"TULCHHA RAM","c":"","res":"PASS"},{"r":"300834","n":"DURGESH REGAR","f":"TULSI RAM REGAR","c":"","res":"PASS"},{"r":"299178","n":"SANJAY KUMAR MEENA","f":"TULSIRAM MEENA","c":"","res":"PASS"},{"r":"293566","n":"DAMODAR BHATI","f":"TULASI RAM","c":"","res":"PASS"},{"r":"311335","n":"CHETRAM MEENA","f":"TULSIRAM MEENA","c":"","res":"PASS"},{"r":"321595","n":"SAPNA RAYANIYA","f":"TULSI RAM RAYNIYA","c":"","res":"PASS"},{"r":"301934","n":"AMIT KUMAR MEENA","f":"TULSIRAM MEENA","c":"","res":"PASS"},{"r":"204429","n":"VISHNU SHARMA","f":"TULSI RAM","c":"","res":"PASS"},{"r":"321117","n":"JAMNA MEGHWAL","f":"TULASI RAM MEGHWAL","c":"","res":"PASS"},{"r":"202827","n":"DHARAM SINGH BAIRWA","f":"TULSI RAM BAIRWA","c":"","res":"PASS"},{"r":"195682","n":"PRASHANT SAINI","f":"TULSIRAM SAINI","c":"","res":"PASS"},{"r":"202461","n":"NEELAM KUMARI MEENA","f":"TULSI RAM MEENA","c":"","res":"PASS"},{"r":"291413","n":"JITENDRA BIDIYASAR","f":"TULACHHA RAM","c":"","res":"PASS"},{"r":"292756","n":"SAYARA RAM MEGHWAL","f":"TULSI RAM","c":"","res":"PASS"},{"r":"285348","n":"MANISHA JATAV","f":"TULSI RAM","c":"","res":"PASS"},{"r":"194831","n":"VINOD DANGI","f":"TULASIRAM","c":"","res":"PASS"},{"r":"298514","n":"DEEPIKA MEENA","f":"TULSIRAM MEENA","c":"","res":"PASS"},{"r":"321908","n":"SONIYA MEENA","f":"TULSIRAM MEENA","c":"","res":"PASS"},{"r":"195868","n":"MANGI LAL","f":"TULACHHA RAM","c":"","res":"PASS"},{"r":"180103","n":"PAYAL KHATIK","f":"TULSIRAM KHATIK","c":"","res":"PASS"},{"r":"199944","n":"GUNJAN MEENA","f":"TUNDARAM MEENA","c":"","res":"PASS"},{"r":"257830","n":"DEEPAK KUMAR TUNGARIA","f":"SHYOJIRAM TUNGARIYA","c":"","res":"PASS"},{"r":"235121","n":"SNEHA CHOUDHARY","f":"TULSI RAM","c":"","res":"PASS"},{"r":"325128","n":"POOJA SAINI","f":"TULSI RAM SAINI","c":"","res":"PASS"},{"r":"308087","n":"PUNIT GARHWAL","f":"TULSI RAM GARHWAL","c":"","res":"PASS"},{"r":"194290","n":"VISHAL KUMAR SUTHAR","f":"TULSHIRAM SUTHAR","c":"","res":"PASS"},{"r":"331994","n":"RAJAT KUMAR","f":"TUHIRAM","c":"","res":"PASS"},{"r":"314492","n":"NEELU KUMARI DHAKAR","f":"TULSIRAM DHAKAR","c":"","res":"PASS"},{"r":"206942","n":"RAVI KUSHWAH","f":"TULSEE RAM","c":"","res":"PASS"},{"r":"204352","n":"SANTOSH MEENA","f":"TULSIRAM MEENA","c":"","res":"PASS"},{"r":"175774","n":"SURENDRA SINGH","f":"TULSI RAM","c":"","res":"PASS"},{"r":"193821","n":"NARENDRA REBARI","f":"TULASI RAM REBARI","c":"","res":"PASS"},{"r":"329581","n":"BAJANTA JAKHAR","f":"TULCHHA RAM JAKHAR","c":"","res":"PASS"},{"r":"313931","n":"MUKESH KUMAR MEENA","f":"TULSIRAM MEENA","c":"","res":"PASS"},{"r":"295937","n":"NARVEER JAJDA","f":"TULCHHA RAM","c":"","res":"PASS"},{"r":"174914","n":"DHARMESH SINGH","f":"TUHIRAM","c":"","res":"PASS"},{"r":"191258","n":"RESHMA MEENA","f":"TULSIRAM MEENA","c":"","res":"PASS"},{"r":"173000","n":"KULDEEP","f":"TULSI RAM","c":"","res":"PASS"},{"r":"272747","n":"DEVENDRA KUMAR GURJAR","f":"TULSIRAM GURJAR","c":"","res":"PASS"},{"r":"170167","n":"ASMITA NAGAR","f":"TULSI RAM NAGAR","c":"","res":"PASS"},{"r":"286875","n":"BHUVNESH KUMARI MEENA","f":"TULSI RAM MEENA","c":"","res":"PASS"},{"r":"288934","n":"MANOJ PARETA","f":"TULSI RAM PARETA","c":"","res":"PASS"},{"r":"247376","n":"ANKIT JANGID","f":"TULSI RAM JANGID","c":"","res":"PASS"},{"r":"257794","n":"KAMLESH","f":"TULSI RAM","c":"","res":"PASS"},{"r":"181941","n":"LOKESH KUMAWAT","f":"TULSIRAM KUMAWAT","c":"","res":"PASS"},{"r":"265525","n":"SHEELA YADAV","f":"TULSI RAM YADAV","c":"","res":"PASS"},{"r":"260290","n":"VANDNA YADAV","f":"TULSIRAM YADAV","c":"","res":"PASS"},{"r":"207208","n":"AKASH","f":"TULSI RAM","c":"","res":"PASS"},{"r":"283685","n":"SORABH YOGI","f":"TUBI YOGI","c":"","res":"PASS"},{"r":"215545","n":"KAMLESH","f":"TULCHHA RAM","c":"","res":"PASS"},{"r":"321109","n":"SHELESH PANDOR","f":"TULSIRAM PANDOR","c":"","res":"PASS"},{"r":"265667","n":"SUSHIL KUMAR HARIJAN","f":"TULASI RAM","c":"","res":"PASS"},{"r":"173194","n":"PRATAP SINGH","f":"TUHI RAM","c":"","res":"PASS"},{"r":"183421","n":"KAILASH BEGAR","f":"TUGNA RAM BEGAR","c":"","res":"PASS"},{"r":"315809","n":"BARKHA VAISHNAV","f":"TULSIRAM VAISHNAV","c":"","res":"PASS"},{"r":"199672","n":"SANJANA MEENA","f":"TUNDA RAM MEENA","c":"","res":"PASS"},{"r":"272034","n":"SURESH KUMAR","f":"TULACHHA RAM","c":"","res":"PASS"},{"r":"159203","n":"MANISHA MINA","f":"TULSI RAM MEENA","c":"","res":"PASS"},{"r":"207884","n":"KRISHNA AHARI","f":"TULSIRAM AHARI","c":"","res":"PASS"},{"r":"331136","n":"PRAKASH JAKHAR","f":"TULACHHA RAM","c":"","res":"PASS"},{"r":"296090","n":"PRIYANKA","f":"TULCHARAM KASWA","c":"","res":"PASS"},{"r":"292427","n":"ABHISHEK FAGODIYA","f":"TULCHHARAM FAGODIYA","c":"","res":"PASS"},{"r":"244259","n":"MAMTA BUNKAR","f":"TULSI RAM BUNKAR","c":"","res":"PASS"},{"r":"170246","n":"DEEPAK NAGAR","f":"TULSI RAAM","c":"","res":"PASS"},{"r":"201839","n":"PINTU KUMAR SAINI","f":"TUNDARAM SAINI","c":"","res":"PASS"},{"r":"163009","n":"JITESH MACHHAR","f":"TULIYA MACHHAR","c":"","res":"PASS"},{"r":"216400","n":"SAROJ","f":"TULSI DAS","c":"","res":"PASS"},{"r":"328662","n":"NEERAJ KUMAR","f":"TULCHHA RAM","c":"","res":"PASS"},{"r":"273168","n":"SODAN SINGH","f":"TUFAN SINH","c":"","res":"PASS"},{"r":"289918","n":"HARSH GAUTAM","f":"TULSIRAM","c":"","res":"PASS"},{"r":"210244","n":"JITENDRA AHARI","f":"TULSIRAM AHARI","c":"","res":"PASS"},{"r":"201189","n":"HEMA MEENA","f":"TULSI RAM MEENA","c":"","res":"PASS"},{"r":"298444","n":"SUBHASH KUMAR MEENA","f":"TULSIRAM MEENA","c":"","res":"PASS"},{"r":"261442","n":"MAHENDRA KUMAR VERMA","f":"TULSI RAM VERMA","c":"","res":"PASS"},{"r":"167757","n":"MANOJ DHANUK","f":"TULSI RAM DHANUK","c":"","res":"PASS"},{"r":"201723","n":"KULDEEP SINGH","f":"TUDARAM","c":"","res":"PASS"},{"r":"324853","n":"MUKESH YADAV","f":"TULLA RAM YADAV","c":"","res":"PASS"}]