[{"r":"223891","n":"RAVI LEGHA","f":"RAM NIWAS","c":"","res":"PASS"},{"r":"151777","n":"LEKHRAJ GURJAR","f":"JEEVRAJ GURJAR","c":"","res":"PASS"},{"r":"268024","n":"KRISHAN KUMAR LEEL","f":"SURAJ MAL LEEL","c":"","res":"PASS"},{"r":"244650","n":"VIKASH LEKHRAJ","f":"MUKESH KUMAR LEKHRAJ","c":"","res":"PASS"},{"r":"183676","n":"RAMCHANDRA LEGHA","f":"BHAIRA RAM LEGHA","c":"","res":"PASS"},{"r":"322482","n":"LEKHRAJ RAWAT","f":"HARDEV RAWAT","c":"","res":"PASS"},{"r":"185884","n":"ASHOK LEGHA","f":"RAMLAL","c":"","res":"PASS"},{"r":"326374","n":"LEELA RAM GURJAR","f":"KAILASH CHAND GURJAR","c":"","res":"PASS"},{"r":"185774","n":"NITU LEGHA","f":"BALRAM LEGHA","c":"","res":"PASS"},{"r":"330861","n":"NITESH LEGA","f":"GYARSI LAL LEGA","c":"","res":"PASS"},{"r":"317932","n":"LEKHARAJ GURJAR","f":"HEMRAJ GURJAR","c":"","res":"PASS"},{"r":"203204","n":"LEKHRAJ MEENA","f":"BANWARI LAL MEENA","c":"","res":"PASS"},{"r":"315288","n":"LEELA KANWAR","f":"SHRAWAN SINGH","c":"","res":"PASS"},{"r":"156872","n":"LEELA GURJAR","f":"NARAYAN LAL GURJAR","c":"","res":"PASS"},{"r":"243381","n":"LEKHRAJ PAREEK","f":"GOPAL LAL PAREEK","c":"","res":"PASS"},{"r":"299251","n":"LEKHRAJ CHOUDHARY","f":"ANIL CHODHARY","c":"","res":"PASS"},{"r":"271301","n":"LERA RAM","f":"VALA RAM","c":"","res":"PASS"},{"r":"326223","n":"LEELARAM GURJAR","f":"UMRAV LAL GURJAR","c":"","res":"PASS"},{"r":"246612","n":"MANISH LEEL","f":"RICHHAPAL LEEL","c":"","res":"PASS"},{"r":"152390","n":"LEKHRAJ GURJAR","f":"RAM LAL","c":"","res":"PASS"},{"r":"274528","n":"LEKHRAJ GURJAR","f":"RAM NARAYAN","c":"","res":"PASS"},{"r":"171711","n":"SHARWAN KUMAR LEGA","f":"NAGA RAM","c":"","res":"PASS"},{"r":"291313","n":"LEKH RAJ","f":"KALU RAM","c":"","res":"PASS"},{"r":"330573","n":"LEELA DEVI CHOUDHARY","f":"HERDEV PRASAD DEVANDA","c":"","res":"PASS"},{"r":"185170","n":"SUNIL KUMAR LEELAWAT","f":"KHEMARAM LEELAWAT","c":"","res":"PASS"},{"r":"302867","n":"LEKHRAJ GOSWAMI","f":"MOHAN LAL GOSWAMI","c":"","res":"PASS"},{"r":"188113","n":"LEELADHAR SAINI","f":"RAMKISHAN SAINI","c":"","res":"PASS"},{"r":"324417","n":"VIKAS KUMAR LEEL","f":"SITARAM LEEL","c":"","res":"PASS"},{"r":"330738","n":"PRAHLAD LEGHA","f":"RAMCHANDRA LEGHA","c":"","res":"PASS"},{"r":"314517","n":"LEKHRAJ JAT","f":"BHANWAR LAL JAT","c":"","res":"PASS"},{"r":"315527","n":"LEKHRAJ GURJAR","f":"DEVA LAL GURJAR","c":"","res":"PASS"},{"r":"183901","n":"LEELADHAR","f":"SWAI RAM","c":"","res":"PASS"},{"r":"252474","n":"LEKHRAJ MEENA","f":"SHANKAR LAL MEENA","c":"","res":"PASS"},{"r":"183650","n":"MUKESH LEGHA","f":"SHRIRAM LEGHA","c":"","res":"PASS"},{"r":"303633","n":"LEKHRAJ MEENA","f":"KAILASH CHAND MEENA","c":"","res":"PASS"},{"r":"268100","n":"LEKHRAJ MEENA","f":"FELEE RAM MEENA","c":"","res":"PASS"},{"r":"255557","n":"SUNIL LEGA","f":"NARAYAN LAL","c":"","res":"PASS"},{"r":"223166","n":"LEELADHAR","f":"RAMSWAROOP","c":"","res":"PASS"},{"r":"196496","n":"SHIMLA LEGHA","f":"BUDHARAM","c":"","res":"PASS"},{"r":"183410","n":"LEKH RAM NAI","f":"PRABHU RAM NAI","c":"","res":"PASS"},{"r":"290271","n":"LEELA","f":"BHANWARLAL","c":"","res":"PASS"},{"r":"295382","n":"LEELA MAKAR","f":"JAGDISH RAM MAKAR","c":"","res":"PASS"},{"r":"170661","n":"JASWANT SINGH LEGHA","f":"JAGADISH KUMAR LEGHA","c":"","res":"PASS"},{"r":"275643","n":"LEKHU KUMAR","f":"MOOL CHAND","c":"","res":"PASS"},{"r":"204474","n":"LEKHRAJ MEENA","f":"RAMESH MEENA","c":"","res":"PASS"},{"r":"176928","n":"LEKHRAJ SINGH","f":"POORAN SINGH","c":"","res":"PASS"},{"r":"182542","n":"LEELA DHAKAD","f":"RAMESHWAR LAL DHAKER","c":"","res":"PASS"},{"r":"203249","n":"LEKHRAJ GURJAR","f":"RAJARAM GURJAR","c":"","res":"PASS"},{"r":"279678","n":"LEELA","f":"NIMBA RAM","c":"","res":"PASS"},{"r":"180357","n":"LEELA GURJAR","f":"DHARMI CHAND GURJAR","c":"","res":"PASS"},{"r":"270599","n":"LEELURAM BAROLIYA","f":"RAMKARAN BAROLIYA","c":"","res":"PASS"},{"r":"185552","n":"VINAY LEGHA","f":"BAL RAM LEGHA","c":"","res":"PASS"},{"r":"188533","n":"LEKHRAJ BAIRWA","f":"DHANRAJ BAIRWA","c":"","res":"PASS"},{"r":"309618","n":"KOMAL LEEL","f":"RAMSWAROOP LEEL","c":"","res":"PASS"},{"r":"258344","n":"LEKHRAJ ATAL","f":"KALURAM ATAL","c":"","res":"PASS"},{"r":"329088","n":"LEELA DEVI","f":"GOPAL RAM","c":"","res":"PASS"},{"r":"238031","n":"LEKHRAJ YADAV","f":"GULLA RAM YADAV","c":"","res":"PASS"},{"r":"261202","n":"LEKH RAM","f":"AJIT SINGH","c":"","res":"PASS"},{"r":"269617","n":"PAPPU LEGA","f":"TARACHAND LEGA","c":"","res":"PASS"},{"r":"326217","n":"LEKHRAJ YADAV","f":"VIKRAM YADAV","c":"","res":"PASS"},{"r":"186131","n":"SIDHARTH LEKHALA","f":"CHETAN RAM","c":"","res":"PASS"},{"r":"180994","n":"LEKHRAJ MEENA","f":"PYARE LAL MEENA","c":"","res":"PASS"},{"r":"213403","n":"LEKH RAM","f":"VIJAY KUMAR","c":"","res":"PASS"},{"r":"189998","n":"LEKHRAJ MEENA","f":"GIRIRAJ MEENA","c":"","res":"PASS"},{"r":"251062","n":"LEKHRAJ JATAV","f":"SAMAY SINGH JATAV","c":"","res":"PASS"},{"r":"186368","n":"MOHAN LAL LEGHA","f":"BHAGIRATH LEGHA","c":"","res":"PASS"},{"r":"157716","n":"LEKHRAM MEENA","f":"RAMSWROOP MEENA","c":"","res":"PASS"},{"r":"164470","n":"LEENA MEHTA","f":"SURENDAR MEHTA","c":"","res":"PASS"},{"r":"230927","n":"LEKHRAJ MEENA","f":"CHOUTH MAL MEENA","c":"","res":"PASS"},{"r":"271231","n":"LEELU SINGH","f":"BHAKHAR SINGH","c":"","res":"PASS"},{"r":"198015","n":"LEELA DHAR","f":"JAGDISH PRASAD","c":"","res":"PASS"},{"r":"192297","n":"LEKHARAJ MEENA","f":"MAHAVEER MEENA","c":"","res":"PASS"},{"r":"181554","n":"LEKHRAJ GURJAR","f":"RAMKUNWAR GURJAR","c":"","res":"PASS"},{"r":"292999","n":"LEELA CHOUDHARY","f":"JEEVAN RAM","c":"","res":"PASS"},{"r":"306705","n":"PRIYANSHU LEEL","f":"GYARSI LAL LEEL","c":"","res":"PASS"},{"r":"175340","n":"LEKHRAJ SINGH","f":"HARI SINGH","c":"","res":"PASS"},{"r":"281118","n":"LEELA","f":"HASTI RAM","c":"","res":"PASS"},{"r":"171154","n":"LEKH RAJ","f":"LALA RAM","c":"","res":"PASS"},{"r":"282599","n":"LEKHRAJ JATAV","f":"MOHAR SINGH JATAV","c":"","res":"PASS"},{"r":"154828","n":"LEKHRAJ MEGHWANSHI","f":"DHANRAJ MEGHWANSHI","c":"","res":"PASS"},{"r":"261612","n":"LEKHRAJ PALSANIYA","f":"SULTAN SINGH PALSANIYA","c":"","res":"PASS"},{"r":"282022","n":"LEKH RAM MINA","f":"SUKH SINGH MINA","c":"","res":"PASS"},{"r":"329662","n":"LEELA CHAUDHARY","f":"RUGHNATH","c":"","res":"PASS"},{"r":"183655","n":"LEKH RAM MEGHWAL","f":"REVANT RAM MEGHWAL","c":"","res":"PASS"},{"r":"153497","n":"LEKHRAJ REGAR","f":"SHANKAR LAL REGAR","c":"","res":"PASS"},{"r":"274752","n":"LEELA MALAV","f":"JHUMKI LAL MALAV","c":"","res":"PASS"},{"r":"294589","n":"LEELA JUNJARIYA","f":"HEMA RAM","c":"","res":"PASS"},{"r":"158889","n":"PRIYANKA LEKHI","f":"KEDAR LEKHI","c":"","res":"PASS"},{"r":"174883","n":"LEKH SINGH","f":"BANAY SINGH","c":"","res":"PASS"},{"r":"188079","n":"LEKHRAJ GURJAR","f":"PUSHP CHAND GURJAR","c":"","res":"PASS"},{"r":"157894","n":"LEKHRAM SAINI","f":"RATAN LAL SAINI","c":"","res":"PASS"},{"r":"267850","n":"LEKHRAJ MEENA","f":"MANOHAR LAL MEENA","c":"","res":"PASS"},{"r":"185802","n":"RAKESH KUMAR LEGHA","f":"BIRMA RAM LEGHA","c":"","res":"PASS"},{"r":"274888","n":"LEELADHAR NAGAR","f":"RAMESHWAR NAGAR","c":"","res":"PASS"},{"r":"185428","n":"LEKHRAM MOOND","f":"HARI RAM MOOND","c":"","res":"PASS"},{"r":"306644","n":"MONIKA LEGA","f":"INDRA SINGH LEGA","c":"","res":"PASS"},{"r":"302464","n":"LEKHRAJ GURJAR","f":"KAMLESH GURJAR","c":"","res":"PASS"},{"r":"154151","n":"LEENA","f":"BABU LAL JAGRIT","c":"","res":"PASS"},{"r":"153187","n":"LEKH RAJ GURJAR","f":"GOPAL GURJAR","c":"","res":"PASS"},{"r":"302346","n":"LEKHRAJ MEENA","f":"SITA RAM MEENA","c":"","res":"PASS"},{"r":"177650","n":"LEKHRAJ REGAR","f":"OM PRAKASH REGAR","c":"","res":"PASS"},{"r":"217473","n":"LEELA DHAR","f":"KRISHAN LAL","c":"","res":"PASS"},{"r":"288814","n":"LEKHARAJ PRAJAPAT","f":"MUKESH PRAJAPAT","c":"","res":"PASS"},{"r":"201511","n":"LEENA CHHIPA","f":"MADANMOHAN CHHIPA","c":"","res":"PASS"},{"r":"274375","n":"LEELA DHAR BHEEL","f":"RAM BHAROSH","c":"","res":"PASS"},{"r":"183891","n":"LEKHRAM","f":"GIRDHARI RAM","c":"","res":"PASS"},{"r":"235668","n":"LEKHRAJ BUGALIYA","f":"RAJESH BUGALIYA","c":"","res":"PASS"},{"r":"172639","n":"LEKHRAJ SINGH","f":"PREM SINGH","c":"","res":"PASS"},{"r":"291939","n":"LEELA","f":"PAPPU RAM","c":"","res":"PASS"},{"r":"257243","n":"LEKHRAJ MEENA","f":"JAGDISH PRASAD MEENA","c":"","res":"PASS"},{"r":"271355","n":"TINKU LEEL","f":"KISHAN LAL LEEL","c":"","res":"PASS"},{"r":"192978","n":"LEKHARAJ MEENA","f":"HARI SHANKER MEENA","c":"","res":"PASS"},{"r":"244908","n":"LEKHRAJ MEENA","f":"BHAGWAN SAHAY MEENA","c":"","res":"PASS"},{"r":"194034","n":"LEELA SUKHWAL","f":"RAMESHWAR LAL SUKHWAL","c":"","res":"PASS"},{"r":"312995","n":"JAGVEER SINGH LEEL","f":"SURESH KUMAR LEEL","c":"","res":"PASS"},{"r":"192949","n":"LEKHRAJ BAIRWA","f":"BHANWAR LAL BAIRWA","c":"","res":"PASS"},{"r":"214848","n":"RITIKA LEGHA","f":"BALJEET RAM","c":"","res":"PASS"},{"r":"244396","n":"LEKHRAJ SAIN","f":"SURESH CHANDRA SAIN","c":"","res":"PASS"},{"r":"284104","n":"LEKHRAJ MEENA","f":"GOPAL LAL MEENA","c":"","res":"PASS"},{"r":"160551","n":"LEKHRAJ PRAJAPAT","f":"JAGDISH PRAJAPAT","c":"","res":"PASS"},{"r":"171306","n":"LEELA","f":"BABU LAL","c":"","res":"PASS"},{"r":"151254","n":"LEKHRAJ","f":"SANWAR SINGH","c":"","res":"PASS"},{"r":"330267","n":"DINESH LEGHA","f":"PREMA RAM","c":"","res":"PASS"},{"r":"208109","n":"LEELA AHARI","f":"AMARAT LAL AHARI","c":"","res":"PASS"},{"r":"297967","n":"LEELA DEWASI","f":"DUNGAR RAM","c":"","res":"PASS"},{"r":"312195","n":"LEELA JAT","f":"GOPI LAL JAT","c":"","res":"PASS"},{"r":"244285","n":"LEELADHAR NODAL","f":"KANA RAM NODAL","c":"","res":"PASS"},{"r":"152701","n":"LEKHRAJ MEENA","f":"DURGA LAL MEENA","c":"","res":"PASS"},{"r":"190147","n":"LEELA DHAKAR","f":"LAXMAN DHAKAR","c":"","res":"PASS"},{"r":"330198","n":"SANVARA RAM LEGA","f":"RUGHNATH","c":"","res":"PASS"},{"r":"316675","n":"LEKHRAJ GURJAR","f":"SHANKAR LAL","c":"","res":"PASS"},{"r":"273189","n":"LEKHRAJ","f":"JAGDISH","c":"","res":"PASS"},{"r":"195564","n":"LEELA KUMARI JAT","f":"KISHAN LAL JAT","c":"","res":"PASS"},{"r":"332688","n":"LETESH SINGH","f":"SATYAVEER SINGH","c":"","res":"PASS"},{"r":"332630","n":"LEELA RAM BAVRIYA","f":"MAHAVEER BAVRIYA","c":"","res":"PASS"},{"r":"286948","n":"LEENA CHANDANI","f":"CHIMAN DAS","c":"","res":"PASS"},{"r":"200385","n":"LEKHRAJ SINGH GURJAR","f":"MUKESH KUMAR GURJAR","c":"","res":"PASS"},{"r":"187703","n":"LEKHRAJ SINGH","f":"DURGA SHANKAR","c":"","res":"PASS"},{"r":"329072","n":"SURENDRA LEGA","f":"KISHNA RAM","c":"","res":"PASS"},{"r":"286850","n":"LEKHRAJ BAIRWA","f":"BADRI LAL","c":"","res":"PASS"},{"r":"298668","n":"LEKHANI SONI","f":"JAGDISH KUMAR SONI","c":"","res":"PASS"},{"r":"211475","n":"LEELARAM GARASIYA","f":"RAMSON GARASIYA","c":"","res":"PASS"},{"r":"314489","n":"LEKHRAJ MEHRA","f":"BABU LAL MEHRA","c":"","res":"PASS"},{"r":"188239","n":"LEELA KUMARI MALI","f":"KALU RAM MALI","c":"","res":"PASS"},{"r":"251297","n":"LEELADHAR PUNIA","f":"BANWARI LAL","c":"","res":"PASS"},{"r":"191787","n":"LEELA KUMARI MEENA","f":"SATYANARAYAN MEENA","c":"","res":"PASS"},{"r":"189012","n":"LEKHRAJ GURJAR","f":"RAMKARAN GURJAR","c":"","res":"PASS"},{"r":"310311","n":"LEELA KUMARI","f":"CHANDAN KUMAR","c":"","res":"PASS"},{"r":"320083","n":"LEELA KUMARI MEENA","f":"AMBA LAL GAMETI","c":"","res":"PASS"},{"r":"257518","n":"LEKHRAJ MEENA","f":"JAGDISH NARAYAN MEENA","c":"","res":"PASS"},{"r":"255619","n":"VIKRAM LEEL","f":"MAHENDRA LEEL","c":"","res":"PASS"},{"r":"172460","n":"TARUN LEGHA","f":"HUKMA RAM","c":"","res":"PASS"},{"r":"156385","n":"LEELA KUMARI MALI","f":"SATYA NARAYAN MALI","c":"","res":"PASS"},{"r":"207111","n":"LEENA LAHRY","f":"RAMJEET LAHRY","c":"","res":"PASS"},{"r":"317760","n":"LEKH RAJ MEENA","f":"SHYONARAYAN MEENA","c":"","res":"PASS"},{"r":"203386","n":"LEKHRAJ GURJAR","f":"BHOLA SINGH GURJAR","c":"","res":"PASS"},{"r":"235314","n":"LEKHRAJ MEENA","f":"RAJENDRA PRASAD MEENA","c":"","res":"PASS"},{"r":"155918","n":"LEKHRAJ MEENA","f":"RAMNIWAS MEENA","c":"","res":"PASS"},{"r":"154255","n":"LEKHARAJ MINA","f":"RAMKISHAN MINA","c":"","res":"PASS"},{"r":"333623","n":"LEKHRAM GURJAR","f":"JAISINGH","c":"","res":"PASS"},{"r":"163948","n":"LEENA PARGI","f":"CHHAGANLAL","c":"","res":"PASS"},{"r":"229033","n":"LEKHA KUMARI","f":"KRISHNA KUMAR","c":"","res":"PASS"},{"r":"269264","n":"LEKH RAJ SAINI","f":"RAMKARAN SAINI","c":"","res":"PASS"},{"r":"313809","n":"LEKHRAJ CHOUDHARY","f":"DHANRAJ JAT","c":"","res":"PASS"},{"r":"152419","n":"LEKHRAJ SEN","f":"RAM SWAROOP","c":"","res":"PASS"},{"r":"214709","n":"LEKHRAM","f":"OM PRAKASH","c":"","res":"PASS"},{"r":"206813","n":"LEKH RAJ","f":"DALEEP","c":"","res":"PASS"},{"r":"270949","n":"LEELA KANWAR","f":"SWROOP SINGH","c":"","res":"PASS"},{"r":"199795","n":"LEKHARAJ MEENA","f":"LALLU PRASAD MEENA","c":"","res":"PASS"},{"r":"327711","n":"LEKHRAJ GURJAR","f":"LEELA RAM GURJAR","c":"","res":"PASS"},{"r":"153544","n":"LEELA GURJAR","f":"BADRI LAL GURJAR","c":"","res":"PASS"},{"r":"314223","n":"LEKHARAJ GURJAR","f":"HANUMAN GURJAR","c":"","res":"PASS"},{"r":"159452","n":"LEKHRAJ GURJAR","f":"JAI SINGH GURJAR","c":"","res":"PASS"},{"r":"327392","n":"LEKHRAJ MEENA","f":"RAMNIWAS MEENA","c":"","res":"PASS"},{"r":"209107","n":"LEELA KUMARI DAMOR","f":"MAGAN LAL DAMOR","c":"","res":"PASS"},{"r":"230682","n":"LEENA BHARTIYA","f":"BABULAL NAGA","c":"","res":"PASS"},{"r":"180856","n":"LEKHRAJ MEENA","f":"PRAMOD KUMAR MEENA","c":"","res":"PASS"},{"r":"208602","n":"LEELA KUMARI ROAT","f":"GANESH LAL ROAT","c":"","res":"PASS"},{"r":"180224","n":"LEKHRAJ MEENA","f":"KHEMRAJ MEENA","c":"","res":"PASS"},{"r":"315454","n":"LEELA KUMARI BAIRWA","f":"RAM PRASAD BAIRWA","c":"","res":"PASS"},{"r":"190121","n":"LEKHRAJ KUMHAR","f":"KAILASH KUMHAR","c":"","res":"PASS"},{"r":"207658","n":"LEELA AHARI","f":"RAMESH AHARI","c":"","res":"PASS"},{"r":"166323","n":"LEELA SHANKAR NAGAR","f":"MAHAVEER NAGAR","c":"","res":"PASS"},{"r":"256616","n":"LEKHRAJ MEENA","f":"SHRI RAMNIWAS MEENA","c":"","res":"PASS"},{"r":"321572","n":"LEELA GARASIYA","f":"GULA RAM","c":"","res":"PASS"},{"r":"310430","n":"LEELA RAM MEGHWAL","f":"BHAGAWANJI MEGHWAL","c":"","res":"PASS"},{"r":"157603","n":"LEKH RAM GURJAR","f":"PYAR SINGH GURJAR","c":"","res":"PASS"},{"r":"249368","n":"RAKESH KUMAR LEEL","f":"RAMSINGH LEEL","c":"","res":"PASS"},{"r":"172084","n":"LEENA","f":"JABAR SINGH","c":"","res":"PASS"},{"r":"319361","n":"LEELA PATEL","f":"RAM LAL PATEL","c":"","res":"PASS"},{"r":"181821","n":"LEKHRAJ PRAJAPAT","f":"KAJOD PRAJAPAT","c":"","res":"PASS"},{"r":"295221","n":"ABHISHEK LEGA","f":"BUDHARAM LEGA","c":"","res":"PASS"},{"r":"234909","n":"MAUSAM LEEL","f":"SURAJ MAL LEEL","c":"","res":"PASS"},{"r":"274186","n":"LEKHARAJ NAGAR","f":"BANE SINGH","c":"","res":"PASS"},{"r":"176292","n":"LEKHRAJ SINGH","f":"DIWAN SINGH","c":"","res":"PASS"},{"r":"154852","n":"LEKHRAJ DHAKER","f":"SATYANARAYAN DHAKER","c":"","res":"PASS"},{"r":"199396","n":"LEKHRAJ GURJAR","f":"RAMSINGH GURJAR","c":"","res":"PASS"},{"r":"265332","n":"LEKHRAJ BALAI","f":"LAXMAN PRASAD BALAI","c":"","res":"PASS"},{"r":"157486","n":"LEELA RAM GURJAR","f":"CHHOTE LAL GURJAR","c":"","res":"PASS"},{"r":"314022","n":"LEKHRAJ JAT","f":"SHRI RAM JAT","c":"","res":"PASS"},{"r":"199414","n":"LEKHRAJ PRAJAPAT","f":"GHANSHYAM PRAJAPAT","c":"","res":"PASS"},{"r":"240186","n":"LEKHRAJ MEENA","f":"BADRI NARAYAN","c":"","res":"PASS"},{"r":"234514","n":"LEKHRAJ MEENA","f":"KAILASH CHAND MEENA","c":"","res":"PASS"},{"r":"185186","n":"JAI PRAKASH LEGHA","f":"BHADAR RAM","c":"","res":"PASS"},{"r":"327537","n":"LEELA RAM SAINI","f":"BHOLARAM SAINI","c":"","res":"PASS"},{"r":"301082","n":"LEELA SALVI","f":"RAMCHANDRA SALVI","c":"","res":"PASS"},{"r":"309450","n":"DINESH KUMAR LEEL","f":"BIRBAL SINGH","c":"","res":"PASS"},{"r":"175132","n":"LEKHNI SHUKLA","f":"SUNIL KUMAR","c":"","res":"PASS"},{"r":"252584","n":"LEKHRAJ BILONIYA","f":"CHOTHMAL BILONIYA","c":"","res":"PASS"},{"r":"280271","n":"LEELA","f":"BHANWARA RAM","c":"","res":"PASS"},{"r":"211427","n":"LEELAWATI KHARADI","f":"RAMA","c":"","res":"PASS"},{"r":"178829","n":"LEELA SHARMA","f":"KAILASH CHANDRA SHARMA","c":"","res":"PASS"},{"r":"153468","n":"LEKHRAJ KHATIK","f":"SATYANARAYAN KHATIK","c":"","res":"PASS"},{"r":"248264","n":"LEELADHAR YADAV","f":"RAMJILAL YADAV","c":"","res":"PASS"},{"r":"298062","n":"POOJA LEHVA","f":"CHATRA RAM LEHVA","c":"","res":"PASS"},{"r":"248291","n":"LEKHRAJ MEENA","f":"GIRRAJ PRASAD MEENA","c":"","res":"PASS"},{"r":"181195","n":"LEKHRAJ MEENA","f":"KAJODMAL MEENA","c":"","res":"PASS"},{"r":"311767","n":"LEKHARAJ GURJAR","f":"RAMAVTAR GURJAR","c":"","res":"PASS"},{"r":"316355","n":"LEKHRAJ CHOUDHARY","f":"RAMAVTAR CHOUDHARY","c":"","res":"PASS"},{"r":"160588","n":"LEKHRAJ MINA","f":"RAJESH KUMAR MINA","c":"","res":"PASS"},{"r":"291254","n":"MANISHA LEGA","f":"RAMNIWASH LEGA","c":"","res":"PASS"},{"r":"202704","n":"LEKHRAJ GURJAR","f":"DHARA SINGH GURJAR","c":"","res":"PASS"},{"r":"176400","n":"LEKHRAJ","f":"GAJRAJ SINGH","c":"","res":"PASS"},{"r":"242359","n":"DUSHYANT LEEL","f":"SANWAR MAL LEEL","c":"","res":"PASS"},{"r":"152030","n":"LEELA KUMARI REGAR","f":"NORAT MAL REGAR","c":"","res":"PASS"},{"r":"303676","n":"LEKHRAJ MEENA","f":"RAMESH CHAND MEENA","c":"","res":"PASS"},{"r":"232334","n":"LEKHRAJ MEENA","f":"RAMPRASAD MEENA","c":"","res":"PASS"},{"r":"154360","n":"LEKHRAJ JHAROTIA","f":"RAMLAL JHAROTIA","c":"","res":"PASS"},{"r":"160121","n":"LEKHRAJ PRAJAPAT","f":"SHIV SINGH","c":"","res":"PASS"},{"r":"312805","n":"LEKHRAJ MEENA","f":"KHEMRAJ MEENA","c":"","res":"PASS"},{"r":"163975","n":"LEELA CHARPOTA","f":"MAKAN CHARPOTA","c":"","res":"PASS"},{"r":"256329","n":"LEKHRAJ MEENA","f":"RAJESH KUMAR MEENA","c":"","res":"PASS"},{"r":"278880","n":"LEELA","f":"GOPA RAM","c":"","res":"PASS"},{"r":"195447","n":"LEHRU LAL DANGI","f":"CHAMPA LAL DANGI","c":"","res":"PASS"},{"r":"175717","n":"LEENESH","f":"MOHAN SINGH","c":"","res":"PASS"},{"r":"199092","n":"LEKH RAJ MEENA","f":"NARSI LAL MEENA","c":"","res":"PASS"},{"r":"229944","n":"LEKHRAJ MEENA","f":"RADHESHYAM MEENA","c":"","res":"PASS"},{"r":"208753","n":"LEELA AHARI","f":"JEEVAN AHARI","c":"","res":"PASS"},{"r":"311938","n":"LEELA VERMA","f":"BHANWAR LAL REGAR","c":"","res":"PASS"},{"r":"164489","n":"LEELA DABI","f":"RAMESH","c":"","res":"PASS"},{"r":"152502","n":"LEKHRAJ REGAR","f":"TARA CHAND JHAROTIYA","c":"","res":"PASS"},{"r":"323570","n":"LEKHRAJ REGAR","f":"SHANKAR LAL REGAR","c":"","res":"PASS"},{"r":"311876","n":"LEKHRAJ GURJAR","f":"HARINARAYAN GURJAR","c":"","res":"PASS"},{"r":"236617","n":"LEKHRAJ ATAL","f":"VINOD KUMAR","c":"","res":"PASS"},{"r":"273356","n":"LEKHRAJ BAGDA","f":"DULICHAND MEENA","c":"","res":"PASS"},{"r":"232043","n":"JAIPRAKASH LEEL","f":"SATYAPAL LEEL","c":"","res":"PASS"},{"r":"180939","n":"LEKH RAJ MEENA","f":"SHYAM LAL MEENA","c":"","res":"PASS"},{"r":"153009","n":"LEKHRAJ JAT","f":"JASRAJ","c":"","res":"PASS"},{"r":"163073","n":"LEELA KUMARI GARASIYA","f":"SHANKER LAL","c":"","res":"PASS"},{"r":"300960","n":"LEELA JAT","f":"SOHAN LAL JAT","c":"","res":"PASS"}]